{
  "title": {
    "media": {
      "url": "",
      "caption": "",
      "credit": ""
    },
    "text": {
      "headline": "Latest updates",
      "text": "<p>timeline</p>"
    }
  },
  "events": [
      {% for post in site.posts %}
      {
        "media": {
          "url": "{{ post.url }}",
          "caption": "{{ post.title | jsonify }}",
          "credit": "{{ post.author | jsonify }}"
        },
        "start_date": {
          "month": "{{ post.date | date: "%-m" }}",
          "day": "{{ post.date | date: "%-d" }}",
          "year": "{{ post.date | date: "%Y" }}"
        },
        "text": {
          "headline": "{{ post.title | jsonify }}",
          "text": "{{ post.content | jsonify }}"
        }
      },
      {% endfor %}
  ]
}
